combinational_lock.v
module dff_7474 (
  input d,
  input clk,
  input pre_n,
  input clr_n, 
  output reg q,
  output q_n
);

  assign q_n = ~q;

  always @(posedge clk) begin
    if (!pre_n) begin
      q <= 1'b1;
    end else if (!clr_n) begin 
      q <= 1'b0;
    end else begin
      q <= d;
    end
  end
endmodule

module shift_register_3bit (
  input clk,
  input data_in,
  input clr_n,
  output q0,
  output q1,
  output q2
);

  wire q0_n, q1_n, q2_n; 
  
  dff_7474 ff0 (
    .d(data_in),
    .clk(clk),
    .pre_n(1'b1),
    .clr_n(clr_n),
    .q(q0),
    .q_n(q0_n)
  );

  dff_7474 ff1 (
    .d(q0),        
    .clk(clk),
    .pre_n(1'b1),
    .clr_n(clr_n),
    .q(q1),
    .q_n(q1_n)
  );

  dff_7474 ff2 (
    .d(q1),        
    .clk(clk),
    .pre_n(1'b1),
    .clr_n(clr_n),
    .q(q2),
    .q_n(q2_n)
  );
endmodule

module lock_control (
  input clk,
  input data_in,
  input clr_n,
  output lock_led,
  output unlock_led,
  output q0,
  output q1,
  output q2
);

//  wire q0, q1, q2;
  wire r0, r1, r2;

  shift_register_3bit sr (
    .clk(clk),
    .data_in(data_in),
    .clr_n(clr_n),
    .q0(q0),
    .q1(q1),
    .q2(q2)
  );
  
  assign r0 = q2;
  assign r1 = q1;
  assign r2 = q0;

  or or1 (lock_led, ~r0, r1, ~r2);
  assign unlock_led = ~lock_led;
endmodule

combinational_lock_tb.v
`timescale 1ns / 1ps

module combinational_lock_tb();
    reg clk;
    reg data_in, clr_n;
    wire lock_led, unlock_led, q0, q1, q2;

    lock_control UUT (
        .clk(clk),
        .data_in(data_in),
        .clr_n(clr_n),
        .unlock_led(unlock_led),
        .lock_led(lock_led),
        .q0(q0),
        .q1(q1),
        .q2(q2)
    );

    initial begin
        clk = 0;
        forever #5 clk = ~clk;  // 10ns clock period
    end
   
    initial begin
        clr_n = 0; 
        #10;
        clr_n = 1;
    end

    initial begin
    	$dumpfile("cmblock.vcd");
    	$dumpvars(0, combinational_lock_tb);
    
        // Test sequence (000)
        @(posedge clk); data_in = 0; #10;
        @(posedge clk); data_in = 0; #10;
        @(posedge clk); data_in = 0; #10;
        @(posedge clk);
        $display("Input: 000, Q: %b%b%b, Lock: %b, Unlock: %b", q2, q1, q0, lock_led, unlock_led);
        @(posedge clk); clr_n = 0; #10;
        @(posedge clk); clr_n = 1; #10;
        
        // Test sequence (011)
        @(posedge clk); data_in = 0; #10;
        @(posedge clk); data_in = 1; #10;
        @(posedge clk); data_in = 1; #10;
        @(posedge clk);
        $display("Input: 011, Q: %b%b%b, Lock: %b, Unlock: %b", q2, q1, q0, lock_led, unlock_led);
        @(posedge clk); clr_n = 0; #10;
        @(posedge clk); clr_n = 1; #10;
        
        // Test sequence (101)
        @(posedge clk); data_in = 1; #10;
        @(posedge clk); data_in = 0; #10;
        @(posedge clk); data_in = 1; #10;
        @(posedge clk);
        $display("Input: 101, Q: %b%b%b, Lock: %b, Unlock: %b", q2, q1, q0, lock_led, unlock_led);
        @(posedge clk); clr_n = 0; #10;
        @(posedge clk); clr_n = 1; #10;
        
        // Test sequence (111)
        @(posedge clk); data_in = 1; #10;
        @(posedge clk); data_in = 1; #10;
        @(posedge clk); data_in = 1; #10;
        @(posedge clk);
        $display("Input: 111, Q: %b%b%b, Lock: %b, Unlock: %b", q2, q1, q0, lock_led, unlock_led);
        @(posedge clk); clr_n = 0; #10;
        @(posedge clk); clr_n = 1; #10;

        $finish;
    end
endmodule

cmblock.vcd
$date
	Mon Oct  7 08:50:13 2024
$end
$version
	Icarus Verilog
$end
$timescale
	1ps
$end
$scope module combinational_lock_tb $end
$var wire 1 ! unlock_led $end
$var wire 1 " q2 $end
$var wire 1 # q1 $end
$var wire 1 $ q0 $end
$var wire 1 % lock_led $end
$var reg 1 & clk $end
$var reg 1 ' clr_n $end
$var reg 1 ( data_in $end
$scope module UUT $end
$var wire 1 & clk $end
$var wire 1 ' clr_n $end
$var wire 1 ( data_in $end
$var wire 1 % lock_led $end
$var wire 1 ) r0 $end
$var wire 1 * r1 $end
$var wire 1 + r2 $end
$var wire 1 ! unlock_led $end
$var wire 1 " q2 $end
$var wire 1 # q1 $end
$var wire 1 $ q0 $end
$scope module sr $end
$var wire 1 & clk $end
$var wire 1 ' clr_n $end
$var wire 1 ( data_in $end
$var wire 1 , q2_n $end
$var wire 1 " q2 $end
$var wire 1 - q1_n $end
$var wire 1 # q1 $end
$var wire 1 . q0_n $end
$var wire 1 $ q0 $end
$scope module ff0 $end
$var wire 1 & clk $end
$var wire 1 ' clr_n $end
$var wire 1 ( d $end
$var wire 1 / pre_n $end
$var wire 1 . q_n $end
$var reg 1 $ q $end
$upscope $end
$scope module ff1 $end
$var wire 1 & clk $end
$var wire 1 ' clr_n $end
$var wire 1 $ d $end
$var wire 1 0 pre_n $end
$var wire 1 - q_n $end
$var reg 1 # q $end
$upscope $end
$scope module ff2 $end
$var wire 1 & clk $end
$var wire 1 ' clr_n $end
$var wire 1 # d $end
$var wire 1 1 pre_n $end
$var wire 1 , q_n $end
$var reg 1 " q $end
$upscope $end
$upscope $end
$upscope $end
$upscope $end
$enddefinitions $end
$comment Show the parameter values. $end
$dumpall
$end
#0
$dumpvars
11
10
1/
x.
x-
x,
x+
x*
x)
x(
0'
0&
x%
x$
x#
x"
x!
$end
#5000
0!
1.
1-
1%
1,
0+
0$
0*
0#
0)
0"
0(
1&
#10000
0&
1'
#15000
1&
#20000
0&
#25000
1&
#30000
0&
#35000
1&
#40000
0&
#45000
0'
1&
#50000
0&
#55000
1'
1&
#60000
0&
#65000
1&
#70000
0&
#75000
0.
1+
1$
1(
1&
#80000
0&
#85000
0-
1*
1#
1&
#90000
0&
#95000
0,
1)
1"
1&
#100000
0&
#105000
0'
1&
#110000
0&
#115000
1'
1&
#120000
0&
#125000
1&
#130000
0&
#135000
1.
0+
0$
0(
1&
#140000
0&
#145000
1!
0%
0.
1-
1+
1$
0*
0#
1(
1&
#150000
0&
#155000
0!
1,
0-
1%
0)
0"
1*
1#
1&
#160000
0&
#165000
0,
1)
1"
0'
1&
#170000
0&
#175000
1'
1&
#180000
0&
#185000
1&
#190000
0&
#195000
1&
#200000
0&
#205000
1&
#210000
0&
#215000
1&
#220000
0&
#225000
0'
1&
#230000
0&
#235000
1'
1&
